django_ltree/__init__.py
django_ltree/apps.py
django_ltree/checks.py
django_ltree/fields.py
django_ltree/functions.py
django_ltree/lookups.py
django_ltree/managers.py
django_ltree/models.py
django_ltree/operations.py
django_ltree/paths.py
django_ltree/migrations/0001_create_extension.py
django_ltree/migrations/__init__.py
django_ltree-0.6.0.dist-info/licenses/LICENSE
django_ltree-0.6.0.dist-info/METADATA
django_ltree-0.6.0.dist-info/WHEEL
django_ltree-0.6.0.dist-info/top_level.txt
django_ltree-0.6.0.dist-info/RECORD
