Metadata-Version: 2.4
Name: django_ltree
Version: 0.6.0
Summary: Django app to support ltree postgres extension
Author-email: Mario César Señoranis Ayala <mariocesar@humanzilla.com>
Project-URL: Source, https://github.com/mariocesar/django_ltree
Project-URL: Tracker, https://github.com/mariocesar/django_ltree/issues
Classifier: Development Status :: 4 - Beta
Classifier: Framework :: Django
Classifier: Framework :: Django :: 2.2
Classifier: Intended Audience :: Developers
Classifier: Operating System :: OS Independent
Classifier: Programming Language :: Python
Classifier: Programming Language :: Python :: 3
Classifier: Programming Language :: Python :: 3.10
Classifier: Programming Language :: Python :: 3.11
Classifier: Programming Language :: Python :: 3.12
Classifier: Programming Language :: Python :: 3.13
Requires-Python: >=3.10
License-File: LICENSE
Requires-Dist: django>=2.2
Provides-Extra: develop
Requires-Dist: pytest; extra == "develop"
Requires-Dist: pytest-django; extra == "develop"
Requires-Dist: pytest-cov; extra == "develop"
Requires-Dist: psycopg[binary]; extra == "develop"
Requires-Dist: twine; extra == "develop"
Requires-Dist: tox; extra == "develop"
Requires-Dist: ruff; extra == "develop"
Dynamic: license-file
